<?xml version="1.0" encoding="utf-8" standalone="yes"?>
<sqlMap namespace="Mercurius.Sparrow.Repositories.Dynamic.ExtensionProperty" xmlns="http://ibatis.apache.org/mapping">
  <alias>
    <typeAlias alias="ExtensionProperty" type="Mercurius.Sparrow.Entities.Dynamic.ExtensionProperty,Mercurius.Sparrow.Entities" />
    <typeAlias alias="ExtensionPropertySO" type="Mercurius.Sparrow.Entities.Dynamic.SO.ExtensionPropertySO,Mercurius.Sparrow.Entities" />
    <typeAlias alias="ExtensionPropertyInstance" type="Mercurius.Sparrow.Entities.Dynamic.ExtensionPropertyInstance,Mercurius.Sparrow.Entities" />
  </alias>
  <statements>
    <!-- 添加或者更新扩展属性信息。 -->
    <update id="CreateOrUpdate" parameterClass="ExtensionProperty">
      <![CDATA[
        IF EXISTS(SELECT * FROM [Dynamic].[ExtensionProperty] WHERE [Id]=#Id#)
          UPDATE [Dynamic].[ExtensionProperty]
          SET
            [Category]=#Category#,
            [Name]=#Name#,
            [Unit]=#Unit#,
            [GroupName]=#GroupName#,
            [ControlId]=#ControlId#,
            [ControlType]=#ControlType#,
            [Placeholder]=#Placeholder#,
            [ControlDataSource]=#ControlDataSource#,
            [ControlMaxLength]=#ControlMaxLength#,
            [ControlCssClass]=#ControlCssClass#,
            [ControlStyle]=#ControlStyle#,
            [ControlValidateRule]=#ControlValidateRule#,
            [Sort]=#Sort#,
            [ModifyUserId]=#ModifyUserId#,
            [ModifyDateTime]=GETDATE()
          WHERE [Id]=#Id#
        ELSE
          INSERT INTO [Dynamic].[ExtensionProperty]
          (
            [Id],
            [Category],
            [Name],
            [Unit],
            [GroupName],
            [ControlId],
            [ControlType],
            [Placeholder],
            [ControlDataSource],
            [ControlMaxLength],
            [ControlCssClass],
            [ControlStyle],
            [ControlValidateRule],
            [Sort],
            [CreateUserId],
            [CreateDateTime]
          )
          VALUES
          (
            NEWID(),
            #Category#,
            #Name#,
            #Unit#,
            #GroupName#,
            #ControlId#,
            #ControlType#,
            #Placeholder#,
            #ControlDataSource#,
            #ControlMaxLength#,
            #ControlCssClass#,
            #ControlStyle#,
            #ControlValidateRule#,
            #Sort#,
            #CreateUserId#,
            GETDATE()
          )
      ]]>
    </update>

    <!-- 删除扩展属性信息。 -->
    <delete id="Remove" parameterClass="Guid">
      <![CDATA[
        DELETE FROM [Dynamic].[ExtensionProperty] WHERE [Id]=#value#
      ]]>
    </delete>

    <!-- 获取分类 -->
    <select id="GetCategories" resultClass="string">
      <![CDATA[
        SELECT DISTINCT([Category]) AS Category FROM [Dynamic].[ExtensionProperty]
      ]]>
    </select>

    <!-- 获取分类下的分组 -->
    <select id="GetGroupNames" parameterClass="string" resultClass="string">
      <![CDATA[
        SELECT
          DISTINCT([GroupName])
        FROM [Dynamic].[ExtensionProperty] 
        WHERE [Category]=#value# AND [GroupName] IS NOT NULL
      ]]>
    </select>

    <!-- 根据主键获取扩展属性信息。 -->
    <select id="GetById" parameterClass="Guid" resultClass="ExtensionProperty">
      <![CDATA[
        SELECT TOP 1 
          a.[Id] AS Id,
          a.[Category] AS Category,
          a.[Name] AS Name,
          a.[Unit] AS Unit,
          a.[GroupName] AS GroupName,
          a.[ControlId] AS ControlId,
          a.[ControlType] AS ControlType,
          a.[Placeholder] AS Placeholder,
          a.[ControlDataSource] AS ControlDataSource,
          a.[ControlMaxLength] AS ControlMaxLength,
          a.[ControlCssClass] AS ControlCssClass,
          a.[ControlStyle] AS ControlStyle,
          a.[ControlValidateRule] AS ControlValidateRule,
          a.[Sort] AS Sort,
          a.[CreateUserId] AS CreateUserId,
          u1.[Name] AS CreateUserName,
          a.[CreateDateTime] AS CreateDateTime,
          a.[ModifyUserId] AS ModifyUserId,
          u2.[Name] AS ModifyUserName,
          a.[ModifyDateTime] AS ModifyDateTime
        FROM [Dynamic].[ExtensionProperty] a
        LEFT JOIN [RBAC].[User] u1
          ON a.CreateUserId=u1.Id
        LEFT JOIN [RBAC].[User] u2
          ON a.ModifyUserId=u2.Id
        WHERE a.[Id]=#value#
      ]]>
    </select>

    <!-- 获取分类下的所有扩展属性信息 -->
    <select id="GetExtensionPropertiesByCategory" parameterClass="Params" resultClass="ExtensionProperty">
      <![CDATA[
        SELECT
          a.[Id] AS Id,
          a.[Name] AS Name,
          a.[Unit] AS Unit,
          a.[GroupName] AS GroupName,
          a.[ControlId] AS ControlId,
          a.[ControlType] AS ControlType,
          a.[Placeholder] AS Placeholder,
          a.[ControlDataSource] AS ControlDataSource,
          a.[ControlMaxLength] AS ControlMaxLength,
          a.[ControlCssClass] AS ControlCssClass,
          a.[ControlStyle] AS ControlStyle,
          a.[ControlValidateRule] AS ControlValidateRule,
          a.[Sort] AS Sort,
          b.[Value] AS Value
        FROM [Dynamic].[ExtensionProperty] a
        LEFT JOIN [Dynamic].[ExtensionPropertyInstance] b
          ON a.Id=b.ExtensionPropertyId AND b.EntityId=#EntityId#
        WHERE [Category]=#Category#
        ORDER BY Sort ASC,GroupName DESC
      ]]>
    </select>

    <!-- 分页返回满足查询条件的扩展属性信息。 -->
    <select id="SearchExtensionProperties" parameterClass="ExtensionPropertySO" resultClass="ExtensionProperty">
      <![CDATA[
        WITH CTE AS(
          SELECT
            a.[Id] AS Id,
            a.[Category] AS Category,
            a.[Name] AS Name,
            a.[Unit] AS Unit,
            a.[GroupName] AS GroupName,
            a.[ControlId] AS ControlId,
            a.[ControlType] AS ControlType,
            a.[Placeholder] AS Placeholder,
            a.[ControlDataSource] AS ControlDataSource,
            a.[ControlMaxLength] AS ControlMaxLength,
            a.[ControlCssClass] AS ControlCssClass,
            a.[ControlStyle] AS ControlStyle,
            a.[ControlValidateRule] AS ControlValidateRule,
            a.[Sort] AS Sort,
            a.[CreateUserId] AS CreateUserId,
            u1.[Name] AS CreateUserName,
            a.[CreateDateTime] AS CreateDateTime,
            a.[ModifyUserId] AS ModifyUserId,
            u2.[Name] AS ModifyUserName,
            a.[ModifyDateTime] AS ModifyDateTime,
            ROW_NUMBER() OVER(ORDER BY a.Category, a.Sort ASC, a.GroupName DESC) AS RowIndex
          FROM [Dynamic].[ExtensionProperty] a
          LEFT JOIN [RBAC].[User] u1
            ON a.CreateUserId=u1.Id
          LEFT JOIN [RBAC].[User] u2
            ON a.ModifyUserId=u2.Id
      ]]>
      <include refid="searchConditions" />
      <![CDATA[
        )
        SELECT * FROM CTE
        WHERE RowIndex BETWEEN (#PageIndex#-1)*#PageSize#+1 AND #PageIndex#*#PageSize#
        ORDER BY RowIndex ASC
      ]]>
    </select>

    <!-- 查询的记录数 -->
    <select id="SearchExtensionPropertiesCount" parameterClass="ExtensionPropertySO" resultClass="int">
      <![CDATA[
        SELECT COUNT(*) FROM [Dynamic].[ExtensionProperty] a
      ]]>
      <include refid="searchConditions" />
    </select>

    <!-- 添加扩展属性实例信息。 -->
    <insert id="CreateInstances" parameterClass="Params">
      <![CDATA[
        BEGIN
          BEGIN TRAN;

          BEGIN TRY
            DELETE FROM [Dynamic].[ExtensionPropertyInstance] WHERE [EntityId]=#EntityId#;
      ]]>
      <iterate property="Instances" open="" conjunction=";" close=";">
        <![CDATA[
		        INSERT INTO [Dynamic].[ExtensionPropertyInstance]
		        (
		          [Id],
			        [ExtensionPropertyId],
			        [EntityId],
			        [Value]
		        )
		        VALUES
		        (
		          NEWID(),
			        #Instances[].ExtensionPropertyId#,
			        #EntityId#,
			        #Instances[].Value#
		        )
        ]]>
      </iterate>
      <![CDATA[
		        COMMIT TRAN;
          END TRY
          BEGIN CATCH
            ROLLBACK TRAN;
          END CATCH
        END
      ]]>
    </insert>

    <!-- 删除扩展属性实例信息。 -->
    <delete id="RemoveInstances" parameterClass="string">
      <![CDATA[
        DELETE FROM [Dynamic].[ExtensionPropertyInstance] WHERE [EntityId]=#value#
      ]]>
    </delete>

    <!-- 查询条件。 -->
    <sql id="searchConditions">
      <dynamic prepend="WHERE">
        <isNotNull property=".">
          <isNotNull property="Category">
            a.[Category]=#Category#
          </isNotNull>
        </isNotNull>
      </dynamic>
    </sql>
  </statements>
</sqlMap>